thinkpulse/__init__.py
thinkpulse/analyzer.py
thinkpulse/bias.py
thinkpulse/cleaner.py
thinkpulse/compare.py
thinkpulse/explain_column.py
thinkpulse/explainer.py
thinkpulse/highlight.py
thinkpulse/insight.py
thinkpulse/summary.py
thinkpulse/utils.py
thinkpulse-0.1.1.dist-info/licenses/LICENSE.txt
thinkpulse-0.1.1.dist-info/METADATA
thinkpulse-0.1.1.dist-info/WHEEL
thinkpulse-0.1.1.dist-info/top_level.txt
thinkpulse-0.1.1.dist-info/RECORD
